MANIFEST.in
README.rst
setup.py
bin/startpro
script/mod/__init__.py
script/mod/hi.py
script/mod/test.py
startpro/VERSION
startpro/__init__.py
startpro/startpro.cfg
startpro.egg-info/PKG-INFO
startpro.egg-info/SOURCES.txt
startpro.egg-info/dependency_links.txt
startpro.egg-info/entry_points.txt
startpro.egg-info/requires.txt
startpro.egg-info/top_level.txt
startpro/common/__init__.py
startpro/common/utils/__init__.py
startpro/common/utils/config.py
startpro/common/utils/log4py.py
startpro/core/__init__.py
startpro/core/constant.py
startpro/core/process.py
startpro/core/settings.py
startpro/core/topcmd.py
startpro/core/commands/__init__.py
startpro/core/commands/create.py
startpro/core/commands/list.py
startpro/core/commands/pkg.py
startpro/core/commands/start.py
startpro/core/utils/__init__.py
startpro/core/utils/loader.py
startpro/core/utils/opts.py
startpro/template/package.py